jinjarope/__init__.py
jinjarope/cli.py
jinjarope/codetree.py
jinjarope/configloaders.py
jinjarope/decorators.py
jinjarope/deepmerge.py
jinjarope/envconfig.py
jinjarope/envglobals.py
jinjarope/environment.py
jinjarope/envtests.py
jinjarope/filetree.py
jinjarope/fsspecloaders.py
jinjarope/htmlfilters.py
jinjarope/iconfilters.py
jinjarope/icons.py
jinjarope/inspectfilters.py
jinjarope/iterfilters.py
jinjarope/jinjafile.py
jinjarope/jinjaloaderfilesystem.py
jinjarope/llm/__init__.py
jinjarope/loaderregistry.py
jinjarope/loaders.py
jinjarope/localization.py
jinjarope/manual.py
jinjarope/mdfilters.py
jinjarope/py.typed
jinjarope/regexfilters.py
jinjarope/resources/filters.toml
jinjarope/resources/functions.toml
jinjarope/resources/humanize_filters.toml
jinjarope/resources/icons.json.gzip
jinjarope/resources/jinja_filters.toml
jinjarope/resources/jinja_functions.toml
jinjarope/resources/jinja_tests.toml
jinjarope/resources/llm_filters.toml
jinjarope/resources/tests.toml
jinjarope/rewriteloader.py
jinjarope/serializefilters.py
jinjarope/tags.py
jinjarope/textfilters.py
jinjarope/undefined.py
jinjarope/utils.py
jinjarope-1.0.7.dist-info/WHEEL
jinjarope-1.0.7.dist-info/entry_points.txt
jinjarope-1.0.7.dist-info/METADATA
jinjarope-1.0.7.dist-info/RECORD
