Metadata-Version: 2.4
Name: jinjarope
Version: 1.0.7
Summary: Jinja2 utilities, loaders & fsspec integration.
Keywords: filesystem,fsspec,internet,jinja2,markdown,templates
Author: Philipp Temminghoff
Author-email: Philipp Temminghoff <philipptemminghoff@gmail.com>
License-Expression: MIT
Classifier: Development Status :: 4 - Beta
Classifier: Intended Audience :: Developers
Classifier: Operating System :: OS Independent
Classifier: Programming Language :: Python :: 3
Classifier: Programming Language :: Python :: 3 :: Only
Classifier: Programming Language :: Python :: 3.13
Classifier: Programming Language :: Python :: 3.14
Classifier: Programming Language :: Python :: Implementation :: CPython
Classifier: Topic :: Internet
Classifier: Topic :: Software Development :: User Interfaces
Requires-Dist: anyenv>=0.4.17
Requires-Dist: epregistry
Requires-Dist: fsspec
Requires-Dist: jinja2
Requires-Dist: universal-pathlib
Requires-Dist: upathtools
Requires-Dist: rich ; extra == 'cli'
Requires-Dist: typer ; extra == 'cli'
Requires-Dist: black ; extra == 'extras'
Requires-Dist: pygments ; extra == 'extras'
Requires-Dist: humanize ; extra == 'extras'
Requires-Dist: natsort ; extra == 'extras'
Requires-Dist: httpx ; extra == 'httpx'
Requires-Dist: pyconify ; extra == 'icons'
Requires-Dist: agentpool[litellm,pillow] ; extra == 'llm'
Requires-Dist: yamling ; extra == 'yaml'
Requires-Python: >=3.13
Project-URL: Documentation, https://phil65.github.io/jinjarope/
Project-URL: Source, https://github.com/phil65/jinjarope
Provides-Extra: cli
Provides-Extra: extras
Provides-Extra: httpx
Provides-Extra: icons
Provides-Extra: llm
Provides-Extra: yaml
